dmap/__init__.py
dmap/c_ir.py
dmap/first_pass.py
dmap/memory.py
dmap/ops.py
dmap/program.py
dmap/tensor.py
dmap-0.0.1.dist-info/LICENSE
dmap-0.0.1.dist-info/METADATA
dmap-0.0.1.dist-info/WHEEL
dmap-0.0.1.dist-info/top_level.txt
dmap-0.0.1.dist-info/RECORD
