Metadata-Version: 2.1
Name: dmap
Version: 0.0.1
Summary: A dimensional mapping tool.
Author: Nathaniel Tomczak
License: MIT
Requires-Python: >=3.7
License-File: LICENSE
Provides-Extra: tests
Requires-Dist: pytest ; extra == 'tests'
